simple_async_mq_server/__init__.py
simple_async_mq_server/__main__.py
simple_async_mq_server/server.py
simple_async_mq_server/server_example.py
simple_async_mq_server/server_example_local.py
simple_async_mq_server/api/__init__.py
simple_async_mq_server/api/dashboard_api.py
simple_async_mq_server/database/__init__.py
simple_async_mq_server/database/db.py
simple_async_mq_server/models/__init__.py
simple_async_mq_server/models/message.py
simple_async_mq_server/models/message_queue.py
simple_async_mq_server/models/message_queue_collection.py
simple_async_mq_server/models/subscriber.py
simple_async_mq_server/utilities/__init__.py
simple_async_mq_server/utilities/config.py
simple_async_mq_server/utilities/helpers.py
simple_async_mq_server/utilities/transformer.py
simple_async_mq_server-0.0.21.dist-info/METADATA
simple_async_mq_server-0.0.21.dist-info/WHEEL
simple_async_mq_server-0.0.21.dist-info/top_level.txt
simple_async_mq_server-0.0.21.dist-info/RECORD
